lincolnlogs/__init__.py
lincolnlogs/build.py
lincolnlogs/notebook.py
lincolnlogs/monkeypatch/__init__.py
lincolnlogs/monkeypatch/deprecation.py
lincolnlogs-1.0.0a1.dist-info/LICENSE
lincolnlogs-1.0.0a1.dist-info/METADATA
lincolnlogs-1.0.0a1.dist-info/WHEEL
lincolnlogs-1.0.0a1.dist-info/top_level.txt
lincolnlogs-1.0.0a1.dist-info/RECORD
